aurora_cli/__init__.py
aurora_cli/concurrent_executor.py
aurora_cli/config.py
aurora_cli/errors.py
aurora_cli/escalation.py
aurora_cli/file_change_aggregator.py
aurora_cli/health_checks.py
aurora_cli/ignore_patterns.py
aurora_cli/main.py
aurora_cli/memory_manager.py
aurora_cli/progress_ui.py
aurora_cli/py.typed
aurora_cli/query_executor.py
aurora_cli/resource_isolation.py
aurora_cli/wizard.py
aurora_cli/agent_discovery/__init__.py
aurora_cli/agent_discovery/manifest.py
aurora_cli/agent_discovery/models.py
aurora_cli/agent_discovery/parser.py
aurora_cli/agent_discovery/scanner.py
aurora_cli/commands/__init__.py
aurora_cli/commands/agents.py
aurora_cli/commands/budget.py
aurora_cli/commands/doctor.py
aurora_cli/commands/friction.py
aurora_cli/commands/goals.py
aurora_cli/commands/headless.py
aurora_cli/commands/health.py
aurora_cli/commands/init.py
aurora_cli/commands/init_helpers.py
aurora_cli/commands/memory.py
aurora_cli/commands/plan.py
aurora_cli/commands/py.typed
aurora_cli/commands/query.py
aurora_cli/commands/soar.py
aurora_cli/commands/spawn.py
aurora_cli/commands/version.py
aurora_cli/configurators/__init__.py
aurora_cli/configurators/agents.py
aurora_cli/configurators/ampcode.py
aurora_cli/configurators/base.py
aurora_cli/configurators/claude.py
aurora_cli/configurators/claude_commands.py
aurora_cli/configurators/droid.py
aurora_cli/configurators/opencode.py
aurora_cli/configurators/registry.py
aurora_cli/configurators/mcp/__init__.py
aurora_cli/configurators/mcp/base.py
aurora_cli/configurators/mcp/claude.py
aurora_cli/configurators/mcp/cline.py
aurora_cli/configurators/mcp/continue_.py
aurora_cli/configurators/mcp/cursor.py
aurora_cli/configurators/mcp/registry.py
aurora_cli/configurators/slash/__init__.py
aurora_cli/configurators/slash/amazon_q.py
aurora_cli/configurators/slash/antigravity.py
aurora_cli/configurators/slash/auggie.py
aurora_cli/configurators/slash/base.py
aurora_cli/configurators/slash/claude.py
aurora_cli/configurators/slash/cline.py
aurora_actr-0.11.1.dist-info/METADATA
aurora_actr-0.11.1.dist-info/WHEEL
aurora_actr-0.11.1.dist-info/entry_points.txt
aurora_actr-0.11.1.dist-info/top_level.txt
aurora_actr-0.11.1.dist-info/RECORD
