Metadata-Version: 2.4
Name: aurora-actr
Version: 0.11.1
Summary: AURORA: Adaptive Unified Reasoning and Orchestration Architecture with MCP Integration
Author-email: AURORA Team <aurora@example.com>
License-Expression: MIT
Project-URL: Homepage, https://github.com/hamr/aurora
Project-URL: Documentation, https://github.com/hamr/aurora/blob/main/README.md
Project-URL: Repository, https://github.com/hamr/aurora
Project-URL: Issues, https://github.com/hamr/aurora/issues
Project-URL: Changelog, https://github.com/hamr/aurora/blob/main/CHANGELOG.md
Keywords: aurora,actr,cognitive-architecture,semantic-search,mcp,reasoning,soar
Classifier: Development Status :: 3 - Alpha
Classifier: Intended Audience :: Developers
Classifier: Programming Language :: Python :: 3
Classifier: Programming Language :: Python :: 3.10
Classifier: Programming Language :: Python :: 3.11
Classifier: Programming Language :: Python :: 3.12
Classifier: Topic :: Software Development :: Libraries :: Python Modules
Classifier: Topic :: Scientific/Engineering :: Artificial Intelligence
Requires-Python: >=3.10
Requires-Dist: pydantic>=2.0.0
Requires-Dist: jsonschema>=4.17.0
Requires-Dist: click>=8.1.0
Requires-Dist: rich>=13.0.0
Requires-Dist: python-frontmatter>=1.0.0
Requires-Dist: jinja2>=3.1.0
Requires-Dist: python-slugify>=8.0.0
Requires-Dist: questionary>=2.0.0
Requires-Dist: pyyaml>=6.0.0
Requires-Dist: tree-sitter>=0.20.0
Requires-Dist: tree-sitter-python>=0.20.0
Requires-Dist: numpy>=1.24.0
Requires-Dist: anthropic>=0.18.0
Requires-Dist: openai>=1.0.0
Requires-Dist: ollama>=0.1.0
Requires-Dist: tenacity>=8.2.0
Requires-Dist: fastmcp>=0.1.0
Provides-Extra: dev
Requires-Dist: pytest>=7.4.0; extra == "dev"
Requires-Dist: pytest-cov>=4.1.0; extra == "dev"
Requires-Dist: pytest-asyncio>=0.21.0; extra == "dev"
Requires-Dist: pytest-benchmark>=4.0.0; extra == "dev"
Requires-Dist: ruff>=0.1.0; extra == "dev"
Requires-Dist: mypy>=1.5.0; extra == "dev"
Requires-Dist: types-jsonschema>=4.0.0; extra == "dev"
Requires-Dist: bandit>=1.7.5; extra == "dev"
Requires-Dist: memory-profiler>=0.61.0; extra == "dev"
